COPYING
README.md
setup.cfg
setup.py
dda_queue.egg-info/PKG-INFO
dda_queue.egg-info/SOURCES.txt
dda_queue.egg-info/dependency_links.txt
dda_queue.egg-info/entry_points.txt
dda_queue.egg-info/not-zip-safe
dda_queue.egg-info/requires.txt
dda_queue.egg-info/top_level.txt
dqueue/__init__.py
dqueue/api.py
dqueue/app.py
dqueue/auth.py
dqueue/cli.py
dqueue/client.py
dqueue/core.py
dqueue/data.py
dqueue/database.py
dqueue/dqtyping.py
dqueue/entry.py
dqueue/extralogging.py
dqueue/proxy.py
dqueue/tools.py